sphinxcontrib/lightbox2/__init__.py
sphinxcontrib/lightbox2/py.typed
sphinxcontrib/lightbox2/assets/css/lightbox.min.css
sphinxcontrib/lightbox2/assets/images/close.png
sphinxcontrib/lightbox2/assets/images/loading.gif
sphinxcontrib/lightbox2/assets/images/next.png
sphinxcontrib/lightbox2/assets/images/prev.png
sphinxcontrib/lightbox2/assets/js/lightbox-plus-jquery.min.js
sphinxcontrib/lightbox2/assets/js/lightbox-plus-jquery.min.map
sphinxcontrib_lightbox2-0.5.0.dist-info/METADATA
sphinxcontrib_lightbox2-0.5.0.dist-info/WHEEL
sphinxcontrib_lightbox2-0.5.0.dist-info/licenses/LICENSE
sphinxcontrib_lightbox2-0.5.0.dist-info/RECORD
