Metadata-Version: 2.4
Name: sphinxcontrib-lightbox2
Version: 0.5.0
Summary: Sphinx extension to add lightbox2 to each figure and image added in HTML
Project-URL: Homepage, https://github.com/jonasehrlich/sphinxcontrib-lightbox2
Project-URL: Repository, https://github.com/jonasehrlich/sphinxcontrib-lightbox2
Project-URL: Documentation, https://sphinxcontrib-lightbox2.readthedocs.io/
Author-email: Jonas Ehrlich <jonas.ehrlich@gmail.com>
License-Expression: MIT
License-File: LICENSE
Requires-Python: >=3.10
Requires-Dist: sphinx>=7
